birdclient/__init__.py
birdclient-0.0.1.dist-info/LICENSE
birdclient-0.0.1.dist-info/METADATA
birdclient-0.0.1.dist-info/WHEEL
birdclient-0.0.1.dist-info/top_level.txt
birdclient-0.0.1.dist-info/RECORD
