Metadata-Version: 2.1
Name: birdclient
Version: 0.0.1
Summary: Python BIRD client
Home-page: https://gitlab.devlabs.linuxassist.net/allworldit/python/birdclient
Author: Nigel Kukard
Author-email: nkukard@lbsd.net
License: UNKNOWN
Platform: UNKNOWN
Classifier: Development Status :: 3 - Alpha
Classifier: Intended Audience :: Developers
Classifier: License :: OSI Approved :: MIT License
Classifier: Operating System :: POSIX :: Linux
Classifier: Programming Language :: Python :: 3 :: Only
Classifier: Topic :: Software Development :: Libraries :: Python Modules
Requires-Python: >=3.6
